README.rst
setup.py
asyncio_redis_cluster/__init__.py
asyncio_redis_cluster/cluster.py
asyncio_redis_cluster/connection.py
asyncio_redis_cluster/crc.py
asyncio_redis_cluster/cursors.py
asyncio_redis_cluster/encoders.py
asyncio_redis_cluster/exceptions.py
asyncio_redis_cluster/log.py
asyncio_redis_cluster/nodemanager.py
asyncio_redis_cluster/pool.py
asyncio_redis_cluster/protocol.py
asyncio_redis_cluster/replies.py
asyncio_redis_cluster.egg-info/PKG-INFO
asyncio_redis_cluster.egg-info/SOURCES.txt
asyncio_redis_cluster.egg-info/dependency_links.txt
asyncio_redis_cluster.egg-info/requires.txt
asyncio_redis_cluster.egg-info/top_level.txt