Metadata-Version: 1.0
Name: asyncio-redis-cluster
Version: 0.1.1
Summary: Cluster support for asyncio Redis client.
Home-page: https://github.com/hackerexperience/asyncio-redis-cluster
Author: Renato Massaro
Author-email: UNKNOWN
License: LICENSE.txt
Platform: UNKNOWN
